Workbook
Name patrimonio: Sheet1!$G$18:$G$18
Name qtd_anos: Sheet1!$G$16
Name rendimento_carteira: Sheet1!$G$11
Name salario: Sheet1!$E$10:$E$10
Name sugestao_investimento: Sheet1!$E$12:$E$12
Name taxa_mensal: Sheet1!$G$17:$G$17

Sheet Sheet1
E9: CONFIGURAÇÕES
E10: Salário | G10: 2000
E11: Rendimento da Carteira | G11: 0.007
E12: Sugestão de Investimento (30%) | G12: =G10*30% -> 600
E14: INVESTIMENTO MENSAL
E15: Quanto investir por mês? | G15: 1260
E16: Por quantos Anos? | G16: 5
E17: Taxa de Rendimento mensal? | G17: 0.0108
E18: Patrimônio acumulado? | G18: =FV(G17,G16*12,-G15) -> 105593.06
E19: Dividendos Mensais? | G19: =G18*$G$11 -> 739.15145
E21: Cenários | F21: Dividendos
E22: Quantos em 2 anos? | F22: 13613 | G22: =F22*G11 -> 95.291
E23: Quantos em 5 anos? | F23: 41888 | G23: =F23*G11 -> 293.216
E24: Quantos em 10 anos? | F24: =FV($G$17,$D27*12,$G$15*-1) -> 306756.66 | G24: =F24*G11 -> 2147.2966
E25: Quantos em 20 anos? | F25: =FV($G$17,$D28*12,$G$15*-1) -> 1420081.7 | G25: =F25*G11 -> 9940.5721
E26: Quantos em 30 anos? | F26: =FV($G$17,$D29*12,$G$15*-1) -> 5460720.1 | G26: =F26*G11 -> 38225.04
D27: 10
D28: 20
D29: 30 | E29: Perfil | F29: Moderado
E30: VALOR A SER INVESTIDO POR MÊS | F30: 200
E32: TIPO DE FII | F32: Percentual Sugerido | G32: Valores
E33: PAPEL | F33: =VLOOKUP($F$29&"-"&E33,Sheet2!A4:$D$22,4,FALSE) -> 0.32 | G33: =F33*$F$30 -> 64
E34: TIJOLO | F34: =VLOOKUP($F$29&"-"&E34,Sheet2!A5:$D$22,4,FALSE) -> 0.35 | G34: =F34*$F$30 -> 70
E35: HÍBRIDOS | F35: =VLOOKUP($F$29&"-"&E35,Sheet2!A6:$D$22,4,FALSE) -> 0.08 | G35: =F35*$F$30 -> 16
E36: FOFs | F36: =VLOOKUP($F$29&"-"&E36,Sheet2!A7:$D$22,4,FALSE) -> 0.05 | G36: =F36*$F$30 -> 10
E37: DESENVOLVIMENTO | F37: =VLOOKUP($F$29&"-"&E37,Sheet2!A8:$D$22,4,FALSE) -> 0.1 | G37: =F37*$F$30 -> 20
E38: HOTELARIAS | F38: =VLOOKUP($F$29&"-"&E38,Sheet2!A9:$D$22,4,FALSE) -> 0.1 | G38: =F38*$F$30 -> 20
G39: =SUM(G33:G38) -> 200

Sheet Sheet2
A4: CHAVE | B4: PERFIL | C4: TIPO DE FII | D4: %
A5: =B5&"-"&C5 -> Conservador-PAPEL | B5: Conservador | C5: PAPEL | D5: 0.3
A6: =B6&"-"&C6 -> Conservador-TIJOLO | B6: Conservador | C6: TIJOLO | D6: 0.5
A7: =B7&"-"&C7 -> Conservador-HÍBRIDOS | B7: Conservador | C7: HÍBRIDOS | D7: 0.1
A8: =B8&"-"&C8 -> Conservador-FOFs | B8: Conservador | C8: FOFs | D8: 0.1
A9: =B9&"-"&C9 -> Conservador-DESENVOLVIMENTO | B9: Conservador | C9: DESENVOLVIMENTO | D9: 0
A10: =B10&"-"&C10 -> Conservador-HOTELARIAS | B10: Conservador | C10: HOTELARIAS | D10: 0
A11: =$B$11&"-"&C11 -> Moderado-PAPEL | B11: Moderado | C11: PAPEL | D11: 0.32
A12: =$B$11&"-"&C12 -> Moderado-TIJOLO | B12: Moderado | C12: TIJOLO | D12: 0.35
A13: =$B$11&"-"&C13 -> Moderado-HÍBRIDOS | B13: Moderado | C13: HÍBRIDOS | D13: 0.08
A14: =$B$11&"-"&C14 -> Moderado-FOFs | B14: Moderado | C14: FOFs | D14: 0.05
A15: =$B$11&"-"&C15 -> Moderado-DESENVOLVIMENTO | B15: Moderado | C15: DESENVOLVIMENTO | D15: 0.1
A16: =$B$11&"-"&C16 -> Moderado-HOTELARIAS | B16: Moderado | C16: HOTELARIAS | D16: 0.1
A17: =$B$17&"-"&C17 -> Agressivo-PAPEL | B17: Agressivo | C17: PAPEL | D17: 0.5
A18: =$B$17&"-"&C18 -> Agressivo-TIJOLO | B18: Agressivo | C18: TIJOLO | D18: 0.1
A19: =$B$17&"-"&C19 -> Agressivo-HÍBRIDOS | B19: Agressivo | C19: HÍBRIDOS | D19: 0.05
A20: =$B$17&"-"&C20 -> Agressivo-FOFs | B20: Agressivo | C20: FOFs | D20: 0.05
A21: =$B$17&"-"&C21 -> Agressivo-DESENVOLVIMENTO | B21: Agressivo | C21: DESENVOLVIMENTO | D21: 0.2
A22: =$B$17&"-"&C22 -> Agressivo-HOTELARIAS | B22: Agressivo | C22: HOTELARIAS | D22: 0.1

Sheet FORMULA ING
C8: # PT-BR ING-EUA O QUE A FÓRMULA FAZ 1 =SOMA() =SUM() Soma todos os números em um intervalo de células. 2 =MÉDIA() =AVERAGE() Calcula a média aritmética dos valores selecionados. 3 =CONT.NÚM() =COUNT() Conta quantas células contêm apenas números. 4 =CONT.VALORES() =COUNTA() Conta células que não estão vazias (texto ou números). 5 =CONT.VAZIO() =COUNTBLANK() Conta quantas células estão vazias no intervalo. 6 =MÁXIMO() =MAX() Retorna o maior valor numérico de um conjunto. 7 =MÍNIMO() =MIN() Retorna o menor valor numérico de um conjunto. 8 =MED() =MEDIAN() Encontra o valor central exato de um conjunto de dados. 9 =MODA.UNO() =MODE.SNGL() Identifica o número que mais se repete na lista. 10 =ARRED() =ROUND() Arredonda um número para uma quantidade específica de dígitos. 11 =TRUNCAR() =TRUNC() Remove as casas decimais sem arredondar o valor. 12 =INT() =INT() Arredonda o número para baixo até o inteiro mais próximo. 13 =ABS() =ABS() Retorna o valor absoluto de um número (sempre positivo). 14 =RAIZQ() =SQRT() Calcula a raiz quadrada de um número positivo. 15 =POTÊNCIA() =POWER() Eleva um número a uma potência específica (exponenciação). 16 =SE() =IF() Testa uma condição e retorna um valor se verdadeiro e outro se falso. 17 =E() =AND() Retorna VERDADEIRO se todas as condições forem verdadeiras. 18 =OU() =OR() Retorna VERDADEIRO se pelo menos uma condição for verdadeira. 19 =NÃO() =NOT() Inverte o valor lógico (transforma Verdadeiro em Falso). 20 =SES() =IFS() Testa múltiplas condições sequencialmente sem aninhar vários SEs. 21 =SEERRO() =IFERROR() Retorna um valor personalizado se a fórmula resultar em erro. 22 =PROCV() =VLOOKUP() Busca um valor na primeira coluna e retorna dado de outra coluna à direita. 23 =PROCX() =XLOOKUP() Versão moderna e superior do PROCV, busca em qualquer direção. 24 =ÍNDICE() =INDEX() Retorna o valor de uma célula baseado na posição (linha/coluna). 25 =CORRESP() =MATCH() Retorna a posição (número) de um item dentro de um intervalo. 26 =DESLOC() =OFFSET() Retorna uma referência deslocada de um ponto inicial por X linhas/colunas. 27 =INDIRETO() =INDIRECT() Converte uma cadeia de texto em uma referência de célula válida. 28 =ESQUERDA() =LEFT() Extrai um número específico de caracteres do início (esquerda) do texto. 29 =DIREITA() =RIGHT() Extrai caracteres do final (direita) de uma string de texto. 30 =EXT.TEXTO() =MID() Extrai caracteres do meio de um texto, definindo início e quantidade. 31 =LOCALIZAR() =FIND() Ensa a posição numérica de um caractere dentro de um texto (case-sensitive). 32 =ARRUMAR() =TRIM() Remove espaços extras, deixando apenas um espaço entre palavras. 33 =MAIÚSCULA() =UPPER() Converte todo o texto para letras maiúsculas. 34 =MINÚSCULA() =LOWER() Converte todo o texto para letras minúsculas. 35 =PRI.MAIÚSCULA() =PROPER() Coloca a primeira letra de cada palavra em maiúscula. 36 =CONCAT() =CONCAT() Une textos de várias células em uma única célula. 37 =UNIRTEXTO() =TEXTJOIN() Une textos definindo um delimitador (vírgula, espaço) e ignorando vazios. 38 =TEXTO() =TEXT() Converte um número ou data em texto com formatação específica. 39 =SUBSTITUIR() =SUBSTITUTE() Substitui texto existente por novo texto dentro de uma string. 40 =HOJE() =TODAY() Retorna a data atual do sistema (atualiza automaticamente). 41 =AGORA() =NOW() Retorna a data e a hora atuais do sistema. 42 =DIA(), =MÊS(), =ANO() =DAY(), =MONTH(), =YEAR() Extraem partes específicas de uma data completa. 43 =DIATRABALHOTOTAL() =NETWORKDAYS() Calcula dias úteis entre duas datas (exclui fins de semana). 44 =FIMMÊS() =EOMONTH() Retorna o último dia do mês, X meses antes ou depois de uma data. 45 =CONT.SE() =COUNTIF() Conta células que atendem a um único critério específico. 46 =SOMASE() =SUMIF() Soma valores que correspondem a um critério definido. 47 =MÉDIASE() =AVERAGEIF() Calcula a média apenas dos valores que atendem a um critério. 48 =ALEATÓRIOENTRE() =RANDBETWEEN() Gera um número inteiro aleatório entre dois limites definidos. 49 =VALIDAR.DADOS =DATA VALIDATION Cria listas suspensas e restringe tipos de entrada na célula. 50 =TABELA DINÂMICA =PIVOT TABLE Ferramenta poderosa para resumir, analisar e cruzar grandes volumes de dados.
